README
pyproject.toml
setup.py
dataerai/CLI.py
dataerai/CommandLib.py
dataerai/Config.py
dataerai/Connection.py
dataerai/MessageLib.py
dataerai/VERSION.py
dataerai/VersionUtils.py
dataerai/__init__.py
dataerai.egg-info/PKG-INFO
dataerai.egg-info/SOURCES.txt
dataerai.egg-info/dependency_links.txt
dataerai.egg-info/entry_points.txt
dataerai.egg-info/requires.txt
dataerai.egg-info/top_level.txt