Metadata-Version: 2.4
Name: dataerai
Version: 0.1.0
Summary: Portal CLI and API
Home-page: https://github.com/dataerai/datafed
Author: Dataerai, LLC
Author-email: info@dataerai.com
Classifier: Programming Language :: Python :: 3
Classifier: License :: OSI Approved :: MIT License
Classifier: Operating System :: OS Independent
Requires-Dist: protobuf>=5.27.1
Requires-Dist: pyzmq>=16
Requires-Dist: wget>=3
Requires-Dist: requests>=2
Requires-Dist: click>=7
Requires-Dist: prompt_toolkit>=2
Dynamic: author
Dynamic: author-email
Dynamic: classifier
Dynamic: description
Dynamic: description-content-type
Dynamic: home-page
Dynamic: requires-dist
Dynamic: summary
